{"topologyName":"perso-detection-rt","config":"{\"topology.workers\":1,\"topology.acker.executors\":1,\"topology.message.timeout.secs\":30,\"topology.eventlogger.executors\":1,\"clustersSecurityConfig\":[{}]}","sources":[{"id":1,"topologyId":1,"topologyComponentBundleId":1,"versionId":1,"name":"KAFKA","description":"","config":{"properties":{"cluster":"1","consumerGroupId":"sam-group","retryDelayPeriodMs":2,"maximumUncommittedOffsets":10000000,"maxRecordsPerPoll":"500","maximumRetries":2147483647,"parallelism":1,"emitNullTuples":false,"partitionRefreshPeriodMs":2000,"securityProtocol":"PLAINTEXT","bootstrapServers":"ip-172-31-18-110.ec2.internal:6667","retryDelayMaximumMs":10000,"fetchMaximumBytesPerPartition":"1048576","firstPollOffsetStrategy":"UNCOMMITTED_EARLIEST","sslTruststoreType":"JKS","clusters":"test-perso","fetchMinimumBytes":"1","sslKeystoreType":"JKS","schemaBranch":"MASTER","sslTrustManagerAlgo":"PKIX","retryInitialDelayMs":0,"sslKeyManagerAlgo":"SunX509","sslProtocol":"TLS","topic":"personalityrecognition","readerSchemaVersion":"1","pollTimeoutMs":200,"offsetCommitPeriodMs":30000}},"reconfigure":false,"outputStreams":[{"id":1,"versionId":1,"streamId":"kafka_stream_1","description":null,"topologyId":1,"fields":[{"name":"web_url","type":"STRING","optional":false},{"name":"snippet","type":"STRING","optional":false},{"name":"byline","type":"STRING","optional":false},{"name":"pub_date","type":"STRING","optional":false},{"name":"headline","type":"STRING","optional":false},{"name":"document_type","type":"STRING","optional":false},{"name":"news_desk","type":"STRING","optional":false},{"name":"timestamp","type":"STRING","optional":false},{"name":"extraversion","type":"STRING","optional":false},{"name":"emotional_stability","type":"STRING","optional":false},{"name":"agreeableness","type":"STRING","optional":false},{"name":"conscientiousness","type":"STRING","optional":false},{"name":"openness_to_experience","type":"STRING","optional":false}],"timestamp":1544914337295}]}],"sinks":[{"id":4,"topologyId":1,"topologyComponentBundleId":16,"versionId":1,"name":"DRUID","description":"","config":{"properties":{"cluster":"1","clusterReplication":1,"segmentGranularity":"FIFTEEN_MINUTE","indexRetryPeriod":"PT10M","maxBatchSize":2000,"maxPendingBatches":5,"discoveryPath":"/druid/discovery","parallelism":1,"clusterPartitions":1,"windowPeriod":"PT10M","aggregatorList":[{"doublemax":{"name":"max_extraversion","fieldName":"extraversion"}},{"doublemax":{"fieldName":"emotional_stability","name":"max_emotional_stability"}},{"doublemax":{"name":"max_openness_to_experience","fieldName":"openness_to_experience"}},{"doublemax":{"name":"max_conscientiousness","fieldName":"conscientiousness"}}],"tranquilityZKconnect":"ip-172-31-18-110.ec2.internal:2181","discardStreamId":"DRUID-DISCARD-STREAM-ID","indexService":"druid/overlord","blockOnFull":true,"timestampField":"processingTime","lingerMillis":0,"queryGranularity":"MINUTE","dataSource":"perso-detection-datasource","clusters":"test-perso","dimensions":["web_url","snippet","pub_date","headline","document_type","news_desk"]}},"reconfigure":false,"timestamp":1544914337295}],"processors":[{"id":3,"topologyId":1,"topologyComponentBundleId":9,"versionId":1,"name":"PROJECTION","description":"","config":{"properties":{"rules":[1]}},"reconfigure":false,"outputStreams":[{"id":2,"versionId":1,"streamId":"projection_transform_stream_3","description":null,"topologyId":1,"fields":[{"name":"web_url","type":"STRING","optional":false},{"name":"snippet","type":"STRING","optional":false},{"name":"pub_date","type":"STRING","optional":false},{"name":"headline","type":"STRING","optional":false},{"name":"document_type","type":"STRING","optional":false},{"name":"news_desk","type":"STRING","optional":false},{"name":"extraversion","type":"STRING","optional":false},{"name":"emotional_stability","type":"STRING","optional":false},{"name":"agreeableness","type":"STRING","optional":false},{"name":"conscientiousness","type":"STRING","optional":false},{"name":"openness_to_experience","type":"STRING","optional":false},{"name":"byline","type":"STRING","optional":false}],"timestamp":1544914337295},{"id":3,"versionId":1,"streamId":"projection_notifier_stream_3","description":null,"topologyId":1,"fields":[{"name":"web_url","type":"STRING","optional":false},{"name":"snippet","type":"STRING","optional":false},{"name":"pub_date","type":"STRING","optional":false},{"name":"headline","type":"STRING","optional":false},{"name":"document_type","type":"STRING","optional":false},{"name":"news_desk","type":"STRING","optional":false},{"name":"extraversion","type":"STRING","optional":false},{"name":"emotional_stability","type":"STRING","optional":false},{"name":"agreeableness","type":"STRING","optional":false},{"name":"conscientiousness","type":"STRING","optional":false},{"name":"openness_to_experience","type":"STRING","optional":false},{"name":"byline","type":"STRING","optional":false}],"timestamp":1544914337295}],"timestamp":1544914337295}],"edges":[{"id":2,"versionId":1,"topologyId":1,"fromId":1,"toId":3,"streamGroupings":[{"streamId":1,"grouping":"SHUFFLE","fields":null}],"timestamp":1544914337295},{"id":3,"versionId":1,"topologyId":1,"fromId":3,"toId":4,"streamGroupings":[{"streamId":2,"grouping":"SHUFFLE","fields":null}],"timestamp":1544914337295}],"rules":[{"reconfigure":false,"id":1,"versionId":1,"topologyId":1,"name":"projection_auto_generated","description":"projection description auto generated","streams":["kafka_stream_1"],"projections":[{"expr":"NORMALIZE_BYLINE(byline) AS byline"},{"expr":"web_url"},{"expr":"snippet"},{"expr":"pub_date"},{"expr":"headline"},{"expr":"document_type"},{"expr":"news_desk"},{"expr":"extraversion"},{"expr":"emotional_stability"},{"expr":"agreeableness"},{"expr":"conscientiousness"},{"expr":"openness_to_experience"}],"sql":"SELECT NORMALIZE_BYLINE(byline) AS \"byline\",web_url,snippet,pub_date,headline,document_type,news_desk,extraversion,emotional_stability,agreeableness,conscientiousness,openness_to_experience FROM kafka_stream_1","actions":[{"__type":"com.hortonworks.streamline.streams.layout.component.rule.action.TransformAction","name":"transformAction","outputStreams":["projection_transform_stream_3"],"transforms":[]}],"outputStreams":["projection_transform_stream_3","projection_notifier_stream_3"],"timestamp":1544914337295}],"windows":[],"branchRules":[],"bundleIdToType":{"1":"KAFKA","16":"DRUID","9":"PROJECTION"},"topologyEditorMetadata":{"topologyId":1,"versionId":1,"data":"{\"sources\":[{\"x\":296.25,\"y\":178.25,\"id\":1}],\"processors\":[{\"x\":587.2583618164062,\"y\":423.3780517578125,\"id\":3}],\"sinks\":[{\"x\":1325.2093505859375,\"y\":147.89291381835938,\"id\":4}],\"graphTransforms\":{\"dragCoords\":[-0.2720907183056198,-1.0994686168268117],\"zoomScale\":0.8022211487208623}}","timestamp":1544914165415}}